warpflow/__init__.py
warpflow/hello.py
warpflow-0.1.0.dist-info/LICENSE
warpflow-0.1.0.dist-info/METADATA
warpflow-0.1.0.dist-info/WHEEL
warpflow-0.1.0.dist-info/top_level.txt
warpflow-0.1.0.dist-info/RECORD
