Metadata-Version: 2.1
Name: warpflow
Version: 0.1.0
Summary: Ready for production feature store framework dedicated to open source.
Author-email: David DeStefano <david@warpflow.ai>
License: MIT License
Project-URL: Homepage, https://github.com/warpflow-ai/warpflow
Project-URL: Repository, https://github.com/warpflow-ai/warpflow
Project-URL: Documentation, https://docs.warpflow.ai/
Requires-Python: >=3.8
License-File: LICENSE
